{
    "index": 12240,
    "title": "Data Scientist",
    "location": "\u65e5\u672c \u6771\u4eac\u90fd \u6e2f\u533a",
    "level": "\u30b7\u30cb\u30a2\u30ec\u30d9\u30eb",
    "skills": [
        "scipy",
        "sql",
        "linux",
        "pandas",
        "aws",
        "python",
        "ai",
        "numpy",
        "docker"
    ],
    "country": "JP",
    "continent": "Asia",
    "url": "https://jp.linkedin.com/jobs/view/data-scientist-at-abeja-inc-1509007069?refId=d8e261c2-b2cf-4a5b-81f2-6a2672dd8f2f&position=25&pageNum=0&trk=guest_job_search_job-result-card_result-card_full-click",
    "eng-level": "Senior"
}