{
    "index": 12918,
    "title": "Data Engineer - AWS",
    "location": "Edinburgh, United Kingdom",
    "level": "Associate",
    "skills": [
        "python",
        "java",
        "aws",
        "sql",
        "scala"
    ],
    "country": "UK",
    "continent": "Europe",
    "url": "https://uk.linkedin.com/jobs/view/data-engineer-aws-at-mbn-solutions-1527349872?refId=8a14da38-ff8c-4675-ad27-c3806a6de76a&position=8&pageNum=0&trk=guest_job_search_job-result-card_result-card_full-click",
    "eng-level": "Associate"
}