{
    "index": 15933,
    "title": "Senior Data Scientist (m/f/d) Medical Devices",
    "location": "Berlin Area, Germany",
    "level": "Associate",
    "skills": [
        "network",
        "statistics",
        "ai",
        "algorithm",
        "programming",
        "mathematics",
        "time series",
        "docker",
        "git"
    ],
    "country": "DE",
    "continent": "Europe",
    "url": "https://de.linkedin.com/jobs/view/senior-data-scientist-m-f-d-medical-devices-at-fresenius-medical-care-1481282038?refId=907b5e23-0dc8-484b-9a70-4e84ef7679d5&position=1&pageNum=0&trk=guest_job_search_job-result-card_result-card_full-click",
    "eng-level": "Associate"
}