{
    "index": 1627,
    "title": "Senior Software Engineer",
    "location": "Pune, Maharashtra, India",
    "level": "Associate",
    "skills": [
        "css",
        "nosql",
        "cassandra",
        "software engineer",
        "aws",
        "mongodb",
        "git",
        "angular",
        "javascript",
        "os",
        "sql",
        "kafka",
        "programming",
        "agile",
        "docker",
        "json"
    ],
    "country": "IN",
    "continent": "Asia",
    "url": "https://in.linkedin.com/jobs/view/senior-software-engineer-at-kobo360-1477852116?refId=70ee6fa9-4db8-4560-aa11-73740f65f652&position=3&pageNum=0&trk=guest_job_search_job-result-card_result-card_full-click",
    "eng-level": "Associate"
}