{
    "index": 17439,
    "title": "Software Engineer",
    "location": "Santiago, CL",
    "level": "Mando intermedio",
    "skills": [
        "java",
        "apache crunch",
        "git",
        "os",
        "oop",
        "algorithm",
        "software engineer",
        "hive",
        "impala",
        "programming",
        "agile"
    ],
    "country": "CL",
    "continent": "South America",
    "url": "https://cl.linkedin.com/jobs/view/software-engineer-at-equifax-chile-s-a-1561174144?refId=51776f0a-9f22-4bd1-927e-12ee6c6eed09&position=22&pageNum=0&trk=guest_job_search_job-result-card_result-card_full-click",
    "eng-level": "Associate"
}