{
    "index": 18331,
    "title": "Technical Solutions Engineer",
    "location": "London, GB",
    "level": "Entry level",
    "skills": [
        "css",
        "nodejs",
        "react",
        "javascript",
        "programming",
        "html"
    ],
    "country": "UK",
    "continent": "Europe",
    "url": "https://uk.linkedin.com/jobs/view/technical-solutions-engineer-at-yieldify-1555668819?refId=50533e82-c028-467b-a249-a0429dfde637&position=22&pageNum=0&trk=guest_job_search_job-result-card_result-card_full-click",
    "eng-level": "Entry level"
}