{
    "index": 19110,
    "title": "Senior Data Engineer",
    "location": "Sydney, New South Wales, Australia",
    "level": "Mid-Senior level",
    "skills": [
        "python",
        "scripting",
        "security",
        "tableau",
        "aws",
        "etl",
        "hdfs",
        "business intelligence",
        "machine learning",
        "spark",
        "data visualization",
        "data structures",
        "hadoop",
        "data warehouse",
        "deep learning"
    ],
    "country": "AU",
    "continent": "Australia",
    "url": "https://au.linkedin.com/jobs/view/senior-data-engineer-at-infotrack-au-1527336254?refId=e61792f0-cb5f-4b97-8f38-9219990c7062&position=3&pageNum=0&trk=guest_job_search_job-result-card_result-card_full-click",
    "eng-level": "Mid-Senior"
}