{
    "index": 19309,
    "title": "Data Engineer",
    "location": "Singapore, Singapore",
    "level": "Associate",
    "skills": [
        "python",
        "tableau",
        "java",
        "linux",
        "sql",
        "c++",
        "programming",
        "hadoop",
        "data warehouse"
    ],
    "country": "SG",
    "continent": "Asia",
    "url": "https://sg.linkedin.com/jobs/view/data-engineer-at-itcs-group-1555044533?refId=363e23d9-bfe3-4973-94c2-63aee4295823&position=10&pageNum=0&trk=guest_job_search_job-result-card_result-card_full-click",
    "eng-level": "Associate"
}