{
    "index": 5322,
    "title": "Data Engineer",
    "location": "H\u00f8rsholm, DK",
    "level": "Nyuddannet",
    "skills": [
        "python",
        "nosql",
        "cassandra",
        "hbase",
        "kubernetes",
        "airflow",
        "linux",
        "sqoop",
        "sql",
        "postgres",
        "spark",
        "programming",
        "hive",
        "data visualization",
        "hadoop",
        "data warehouse",
        "docker"
    ],
    "country": "DK",
    "continent": "Europe",
    "url": "https://dk.linkedin.com/jobs/view/data-engineer-at-coresearch-a-s-1547742535?refId=70fb277a-cfc7-4ac6-bce3-0acf5fd14009&position=23&pageNum=0&trk=guest_job_search_job-result-card_result-card_full-click",
    "eng-level": "Entry level"
}