{
    "index": 6484,
    "title": "R&D Project Engineer (Automation)",
    "location": "Cork, IE",
    "level": "Entry level",
    "skills": [
        "excel",
        "server",
        "functional",
        "os",
        "sql",
        "programming",
        "project management",
        "sql server"
    ],
    "country": "IE",
    "continent": "Europe",
    "url": "https://ie.linkedin.com/jobs/view/r-d-project-engineer-automation-at-alcon-1566283013?refId=2a1c9d08-9f96-4f00-b0da-a8d420d01002&position=6&pageNum=0&trk=guest_job_search_job-result-card_result-card_full-click",
    "eng-level": "Entry level"
}