{
    "index": 8347,
    "title": "Data Engineer",
    "location": "Melbourne, AU",
    "level": "Entry level",
    "skills": [
        "scripting",
        "elasticsearch",
        "java",
        "jenkins",
        "etl",
        "devops",
        "scala",
        "spark",
        "programming",
        "agile",
        "mathematics",
        "hadoop",
        "bash",
        "docker",
        "git",
        "scrum"
    ],
    "country": "AU",
    "continent": "Australia",
    "url": "https://au.linkedin.com/jobs/view/data-engineer-at-quantexa-1484854516?refId=256bd7aa-585d-496f-ade0-1a5be732e758&position=17&pageNum=0&trk=guest_job_search_job-result-card_result-card_full-click",
    "eng-level": "Entry level"
}