{
    "index": 9447,
    "title": "Senior Data Engineer",
    "location": "Beijing, CN",
    "level": "\u52a9\u7406",
    "skills": [
        "s3",
        "etl",
        "airflow",
        "machine learning",
        "scala",
        "programming",
        "spark",
        "redshift"
    ],
    "country": "CN",
    "continent": "Asia",
    "url": "https://cn.linkedin.com/jobs/view/senior-data-engineer-at-tubi-1525325208?refId=3f0a7ca5-a7e1-4261-b12d-45d983088964&position=9&pageNum=0&trk=guest_job_search_job-result-card_result-card_full-click",
    "eng-level": "Senior"
}