{
    "index": 9510,
    "title": "Software Engineer",
    "location": "Melbourne, Australia",
    "level": "Associate",
    "skills": [
        "python",
        "network",
        "scripting",
        "oracle",
        "software engineer",
        "etl",
        "javascript",
        "functional",
        "sql",
        "c++",
        "programming",
        "c#",
        "data structures",
        "oop",
        "c"
    ],
    "country": "AU",
    "continent": "Australia",
    "url": "https://au.linkedin.com/jobs/view/software-engineer-at-synchronoss-technologies-1558998491?refId=a9c53f1a-4ed3-49e6-b40e-6b9e0a937ada&position=22&pageNum=0&trk=guest_job_search_job-result-card_result-card_full-click",
    "eng-level": "Associate"
}